gitcc/__init__.py
gitcc/commit_validator.py
gitcc/git_hook.py
gitcc/main.py
gitcc/utility.py
gitcc/validation.py
gitcc-2.0.6.dist-info/METADATA
gitcc-2.0.6.dist-info/WHEEL
gitcc-2.0.6.dist-info/entry_points.txt
gitcc-2.0.6.dist-info/top_level.txt
gitcc-2.0.6.dist-info/zip-safe
gitcc-2.0.6.dist-info/RECORD
