Metadata-Version: 2.1
Name: gitcc
Version: 2.0.6
Summary: GIT Commit Check - check the commit for certain rules
Home-page: https://github.com/IceflowRE/gitcc
Author: Iceflower S
Author-email: iceflower@gmx.de
License: MIT
Keywords: git commit naming checker
Classifier: Programming Language :: Python :: 3.10
Classifier: License :: OSI Approved :: MIT License
Classifier: Development Status :: 5 - Production/Stable
Classifier: Operating System :: OS Independent
Classifier: Intended Audience :: Developers
Classifier: Natural Language :: English
Classifier: Environment :: Console
Requires-Python: >=3.9
Requires-Dist: GitPython ==3.1.41
Provides-Extra: dev
Requires-Dist: flake8 ; extra == 'dev'
Requires-Dist: wemake-python-styleguide ; extra == 'dev'
Requires-Dist: flake8-2020 ; extra == 'dev'
Requires-Dist: flake8-builtins ; extra == 'dev'
Requires-Dist: flake8-comprehensions ; extra == 'dev'
Requires-Dist: flake8-docstrings ; extra == 'dev'
Requires-Dist: flake8-multiline-containers ; extra == 'dev'
Requires-Dist: flake8-use-fstring ; extra == 'dev'
Requires-Dist: flake8-simplify ; extra == 'dev'
Requires-Dist: mypy ; extra == 'dev'
Requires-Dist: pylint ; extra == 'dev'
Requires-Dist: pyroma ; extra == 'dev'
Requires-Dist: setuptools ; extra == 'dev'
Requires-Dist: twine >=4.0.0 ; extra == 'dev'
